{
  "alerts": [
    {
      "title": "सूरत में अंतरराष्ट्रीय क्रिप्टो स्कैम का भंडाफोड़",
      "message": "सूरत DCB ने दो युवकों को पकड़ा जो चीन-पाकिस्तान-म्यांमार से निर्देश लेकर Telegram व Binance के ज़रिए करोड़ों की धोखाधड़ी कर रहे थे। ₹2.28 लाख की ब्रांडेड सामान रिफंड स्कैम का भी खुलासा हुआ।"
    },
    {
      "title": "देहरादून STF ने साइबर फ्रॉड सेंटर पर मारा छापा",
      "message": "Basuli क्षेत्र में एक होमस्टे को साइबर ठगी के अड्डे के रूप में इस्तेमाल किया जा रहा था। STF ने 6 आरोपियों को पकड़ा और ₹10.83 करोड़ से जुड़े दस्तावेज व उपकरण ज़ब्त किए।"
    },
    {
      "title": "नकली WhatsApp ट्रैफिक चालान से सावधान",
      "message": "WhatsApp पर ट्रैफिक चालान के बहाने APK भेजे जा रहे हैं। डाउनलोड करते ही मोबाइल का पूरा नियंत्रण स्कैमर्स को मिल सकता है। सरकारी पोर्टल से ही चालान जांचें और 1930 पर शिकायत करें।"
    },
    {
      "title": "हैदराबाद में KYC बहाने APK भेजकर ₹3.92 लाख की ठगी",
      "message": "सरकारी कर्मचारी को KYC अपडेट का झांसा देकर स्कैमर्स ने APK भेजा। इंस्टॉल करते ही अकाउंट से ₹3.92 लाख उड़ा लिए। पुलिस ने चेताया – बैंक कभी APK इंस्टॉल करने को नहीं कहते।"
    }
  ]
}

   
